imgPreprocessor/ColorFilter.py
imgPreprocessor/CountFace.py
imgPreprocessor/CustomBlurFilter.py
imgPreprocessor/__init__.py
imgPreprocessor/color_extractor.py
imgPreprocessor/delexif.py
imgpreprocessor-1.0.4.dist-info/METADATA
imgpreprocessor-1.0.4.dist-info/WHEEL
imgpreprocessor-1.0.4.dist-info/licenses/LICENSE
imgpreprocessor-1.0.4.dist-info/RECORD
