Metadata-Version: 2.3
Name: imgPreprocessor
Version: 1.0.4
Summary: Image Preprocessor with Five Different Functions
Project-URL: Homepage, https://github.com/GarlicCook/library_repo
Project-URL: Issues, https://github.com/GarlicCook/library_repo/issues
Author-email: GarlicCook <kms300508@gmail.com>, ugyo <rss1234567@hanyang.ac.kr>, jaesung05 <1004jaesung@gmail.com>, rlaehdrbb <donggyug713@gmail.com>, hong02jp <hong02jp@gmail.com>
Maintainer-email: ugyo <rss1234567@hanyang.ac.kr>
Classifier: License :: OSI Approved :: MIT License
Classifier: Operating System :: OS Independent
Classifier: Programming Language :: Python :: 3
Requires-Python: >=3.12.6
Requires-Dist: matplotlib>=3.9.3
Requires-Dist: numpy>=1.19.0
Requires-Dist: opencv-python>=4.10.0.84
Requires-Dist: piexif>=1.1.3
Requires-Dist: pillow>=11.0.0
Requires-Dist: scikit-learn>=1.5.2
